zeppelin_handy_helpers/__init__.py
zeppelin_handy_helpers/argumentsactions.py
zeppelin_handy_helpers/handlers.py
zeppelin_handy_helpers/utils.py
zeppelin_handy_helpers-0.0.1a2.data/scripts/zhh
zeppelin_handy_helpers-0.0.1a2.dist-info/DESCRIPTION.rst
zeppelin_handy_helpers-0.0.1a2.dist-info/METADATA
zeppelin_handy_helpers-0.0.1a2.dist-info/RECORD
zeppelin_handy_helpers-0.0.1a2.dist-info/WHEEL
zeppelin_handy_helpers-0.0.1a2.dist-info/metadata.json
zeppelin_handy_helpers-0.0.1a2.dist-info/top_level.txt
