Metadata-Version: 2.0
Name: zeppelin-handy-helpers
Version: 0.0.1a2
Summary: Console tool for zeppelin
Home-page: https://github.com/sbilello/zeppelin-handy-helper
Author: Sergio Bilello
Author-email: sergio.bilello@gmail.com
License: MIT
Download-URL: https://github.com/sbilello/zeppelin-handy-helpers/archive/0.0.1-alpha2.tar.gz
Keywords: helpers,console,zeppelin,notifier,monitoring
Platform: UNKNOWN
Classifier: Development Status :: 3 - Alpha
Classifier: Programming Language :: Python :: 2.7
Requires-Dist: enum
Requires-Dist: requests
Requires-Dist: animation
